calvineComments/__init__.py
calvineComments/settings.py
calvineComments/test_settings.py
calvineComments/urls.py
calvineComments/wsgi.py
comments/__init__.py
comments/admin.py
comments/apps.py
comments/forms.py
comments/models.py
comments/views.py
comments/migrations/0001_initial.py
comments/migrations/__init__.py
comments/tests/__init__.py
comments/tests/test_admin.py
comments/tests/test_forms.py
comments/tests/test_models.py
comments/tests/test_views.py
django_calvo_comments-0.0.15.dist-info/LICENSE
django_calvo_comments-0.0.15.dist-info/METADATA
django_calvo_comments-0.0.15.dist-info/WHEEL
django_calvo_comments-0.0.15.dist-info/top_level.txt
django_calvo_comments-0.0.15.dist-info/RECORD
